benzole/__init__.py
benzole/cli/__init__.py
benzole/cli/__main__.py
benzole/utils/__init__.py
benzole/utils/mapper.py
benzole/utils/types/__init__.py
benzole-0.0.2.dist-info/LICENSE
benzole-0.0.2.dist-info/METADATA
benzole-0.0.2.dist-info/WHEEL
benzole-0.0.2.dist-info/top_level.txt
benzole-0.0.2.dist-info/RECORD
