Metadata-Version: 2.1
Name: benzole
Version: 0.0.2
Summary: Create web apps with new way
Home-page: https://github.com/kritibytes/benzole
Author: kritibytes
Author-email: kritibytes@gmail.com
License: UNKNOWN
Platform: UNKNOWN
Classifier: Programming Language :: Python :: 3
Classifier: License :: OSI Approved :: MIT License
Classifier: Operating System :: OS Independent
Classifier: Topic :: Software Development
Classifier: Natural Language :: English
Requires-Python: >=3.6
License-File: LICENSE
Requires-Dist: click
Requires-Dist: myp
